[
    {
        "title": "Home",
        "route": "/",
        "data": []
    },
    {
        "title": "About",
        "route": "/about",
        "data": []
    },
    {
        "title": "Paket Wisata",
        "route": "/tour-packages",
        "data": [
            {
                "contentType" : "banner",
                "contentData" : {
                    "imageUrl" : "imageurl",
                    "route" : "/route"
                }
            },
            {
                "contentType" : "schedule",
                "contentData" : {
                    "schedules" : "TBD",
                    "route" : "/route"
                }
            }
        ]
    }
]
